pyxon/__init__.py
pyxon/axon_server_adapter/__init__.py
pyxon/axon_server_adapter/client/__init__.py
pyxon/axon_server_adapter/client/client.py
pyxon/axon_server_adapter/command_handling/__init__.py
pyxon/axon_server_adapter/command_handling/gateway.py
pyxon/axon_server_adapter/query_handling/__init__.py
pyxon/axon_server_adapter/query_handling/gateway.py
pyxon/core/__init__.py
pyxon/core/command_handling/__init__.py
pyxon/core/command_handling/gateway.py
pyxon/core/command_handling/registry.py
pyxon/core/messaging/__init__.py
pyxon/core/messaging/response_types.py
pyxon/core/modelling/__init__.py
pyxon/core/modelling/command.py
pyxon/core/query_handling/__init__.py
pyxon/core/query_handling/gateway.py
pyxon-0.0.2.dist-info/LICENSE
pyxon-0.0.2.dist-info/METADATA
pyxon-0.0.2.dist-info/WHEEL
pyxon-0.0.2.dist-info/top_level.txt
pyxon-0.0.2.dist-info/RECORD
