Metadata-Version: 2.1
Name: pyxon
Version: 0.0.2
Summary: Pyxon framework
Home-page: https://github.com/pyxon/core
Author: Pavel V. Pristupa
Author-email: pristupa@gmail.com
License: UNKNOWN
Platform: UNKNOWN
Classifier: Programming Language :: Python :: 3
Classifier: License :: OSI Approved :: GNU General Public License v3 (GPLv3)
Classifier: Operating System :: OS Independent
Requires-Python: >=3.6, <3.7
Requires-Dist: injector (==0.15.0)
Requires-Dist: persipy (==1.0.0)
Requires-Dist: winter (==2.3.1)
